master_tuyul_sdk/__init__.py
master_tuyul_sdk/Cipher/__init__.py
master_tuyul_sdk/Cipher/__utils__.py
master_tuyul_sdk/Cipher/Password.py
master_tuyul_sdk/Cipher/Salt.py
master_tuyul_sdk/Database/__base__.py
master_tuyul_sdk/Database/__init__.py
master_tuyul_sdk/Database/sql.py
master_tuyul_sdk/Gmail/__init__.py
master_tuyul_sdk/Gmail/__mail__.py
master_tuyul_sdk/Gmail/__utils__.py
master_tuyul_sdk/Provider/__httpx__.py
master_tuyul_sdk/Provider/__init__.py
master_tuyul_sdk/Provider/__requests__.py
master_tuyul_sdk/Provider/__utils__.py
master_tuyul_sdk/Provider/_certificate/__init__.py
master_tuyul_sdk/Provider/_certificate/cacert.pem
master_tuyul_sdk/Provider/Connection/__init__.py
master_tuyul_sdk/Provider/Connection/__utils__.py
master_tuyul_sdk/Utils/__init__.py
master_tuyul_sdk/Utils/Clear.py
master_tuyul_sdk/Utils/Color.py
master_tuyul_sdk/Utils/HexBytes.py
master_tuyul_sdk/Utils/Input.py
master_tuyul_sdk/Utils/Line.py
master_tuyul_sdk/Utils/Log.py
master_tuyul_sdk/Utils/Progress.py
master_tuyul_sdk/Utils/UserAgent.py
master_tuyul_sdk-0.1.2.dist-info/WHEEL
master_tuyul_sdk-0.1.2.dist-info/METADATA
master_tuyul_sdk-0.1.2.dist-info/RECORD
